cellpose_omni/__init__.py
cellpose_omni/__main__.py
cellpose_omni/core.py
cellpose_omni/dynamics.py
cellpose_omni/io.py
cellpose_omni/metrics.py
cellpose_omni/models.py
cellpose_omni/plot.py
cellpose_omni/resnet_style.py
cellpose_omni/resnet_torch.py
cellpose_omni/test_mkl.py
cellpose_omni/transforms.py
cellpose_omni/utils.py
cellpose_omni/contrib/__init__.py
cellpose_omni/contrib/distributed_segmentation.py
cellpose_omni/gui/gui.py
cellpose_omni/gui/guiparts.py
cellpose_omni/gui/io.py
cellpose_omni/gui/menus.py
cellpose_omni/gui/qt.conf
cellpose_omni/key/cellpose-data-writer.json
cellpose_omni/logo/cellpose.ico
cellpose_omni/logo/logo.png
cellpose_omni-0.9.1.dist-info/LICENSE
cellpose_omni-0.9.1.dist-info/METADATA
cellpose_omni-0.9.1.dist-info/WHEEL
cellpose_omni-0.9.1.dist-info/entry_points.txt
cellpose_omni-0.9.1.dist-info/top_level.txt
cellpose_omni-0.9.1.dist-info/RECORD
