Metadata-Version: 2.1
Name: cellpose-omni
Version: 0.9.1
Summary: cellpose fork developed for omnipose
Home-page: https://github.com/kevinjohncutler/cellpose
Author: Kevin Cutler
Author-email: kevinjohncutler@outlook.com
License: BSD
Classifier: Programming Language :: Python :: 3
Classifier: License :: OSI Approved :: BSD License
Classifier: Operating System :: OS Independent
License-File: LICENSE
Requires-Dist: numpy (>=1.22.4)
Requires-Dist: scipy
Requires-Dist: natsort
Requires-Dist: tifffile
Requires-Dist: tqdm
Requires-Dist: numba
Requires-Dist: torch (>=1.6)
Requires-Dist: opencv-python-headless
Requires-Dist: fastremap
Requires-Dist: imagecodecs
Provides-Extra: all
Requires-Dist: pyqtgraph (>=0.12.4) ; extra == 'all'
Requires-Dist: PyQt6.sip ; extra == 'all'
Requires-Dist: PyQt6 ; extra == 'all'
Requires-Dist: google-cloud-storage ; extra == 'all'
Requires-Dist: omnipose-theme ; extra == 'all'
Requires-Dist: superqt ; extra == 'all'
Requires-Dist: colour ; extra == 'all'
Requires-Dist: darkdetect ; extra == 'all'
Requires-Dist: scikit-image ; extra == 'all'
Requires-Dist: scikit-learn ; extra == 'all'
Requires-Dist: edt ; extra == 'all'
Requires-Dist: torch-optimizer ; extra == 'all'
Requires-Dist: ncolor (>=1.2.1) ; extra == 'all'
Provides-Extra: distributed
Requires-Dist: dask ; extra == 'distributed'
Requires-Dist: dask-image ; extra == 'distributed'
Requires-Dist: scikit-learn ; extra == 'distributed'
Provides-Extra: docs
Requires-Dist: sphinx (>=3.0) ; extra == 'docs'
Requires-Dist: sphinxcontrib-apidoc ; extra == 'docs'
Requires-Dist: sphinx-rtd-theme ; extra == 'docs'
Provides-Extra: gui
Requires-Dist: pyqtgraph (>=0.12.4) ; extra == 'gui'
Requires-Dist: PyQt6.sip ; extra == 'gui'
Requires-Dist: PyQt6 ; extra == 'gui'
Requires-Dist: google-cloud-storage ; extra == 'gui'
Requires-Dist: omnipose-theme ; extra == 'gui'
Requires-Dist: superqt ; extra == 'gui'
Requires-Dist: colour ; extra == 'gui'
Requires-Dist: darkdetect ; extra == 'gui'
Provides-Extra: omni
Requires-Dist: scikit-image ; extra == 'omni'
Requires-Dist: scikit-learn ; extra == 'omni'
Requires-Dist: edt ; extra == 'omni'
Requires-Dist: torch-optimizer ; extra == 'omni'
Requires-Dist: ncolor (>=1.2.1) ; extra == 'omni'
